dependency_management/Helper.py
dependency_management/__init__.py
dependency_management/requirements/AnyOneOfRequirements.py
dependency_management/requirements/CabalRequirement.py
dependency_management/requirements/CargoRequirement.py
dependency_management/requirements/ComposerRequirement.py
dependency_management/requirements/CondaRequirement.py
dependency_management/requirements/DistributionRequirement.py
dependency_management/requirements/ExecutableRequirement.py
dependency_management/requirements/GemRequirement.py
dependency_management/requirements/GoRequirement.py
dependency_management/requirements/JuliaRequirement.py
dependency_management/requirements/LuarocksRequirement.py
dependency_management/requirements/MavenRequirement.py
dependency_management/requirements/NpmRequirement.py
dependency_management/requirements/PackageRequirement.py
dependency_management/requirements/PipRequirement.py
dependency_management/requirements/PythonImportRequirement.py
dependency_management/requirements/RscriptRequirement.py
dependency_management/requirements/__init__.py
dependency_management-0.4.0.dist-info/DESCRIPTION.rst
dependency_management-0.4.0.dist-info/METADATA
dependency_management-0.4.0.dist-info/RECORD
dependency_management-0.4.0.dist-info/WHEEL
dependency_management-0.4.0.dist-info/metadata.json
dependency_management-0.4.0.dist-info/top_level.txt
